{
    "required": true,
    "package": "dev.tr7zw.firstperson.mixins",
    "compatibilityLevel": "JAVA_8",
    "mixins": [],
    "client": [
        "HeldItemRendererMixin",
        "WorldRendererMixin",
        "FishingBobberRendererMixin",
        "RenderDispatcherMixin",
        "HeldItemFeatureRendererMixin",
        "ModelPartMixin",
        "LivingEntityRendererMixin",
        "FeatureRendererMixin",
        "ArmorFeatureRendererMixin",
        "StuckInBodyLayerMixin",
        "ElytraLayerMixin",
        "PlayerRendererMixin",
        "CustomHeadLayerMixin",
        "PlayerModelMixin",
        "PlayerMixin",
        "AgeableListModelMixin"
    ],
    "injectors": {
        "defaultRequire": 1
    }
}
